MANIFEST.in
README.md
requirements.txt
setup.py
crowsnest_capabilities/__init__.py
crowsnest_capabilities/exceptions.py
crowsnest_capabilities/loader.py
crowsnest_capabilities/models.py
crowsnest_capabilities/structure.py
crowsnest_capabilities.egg-info/PKG-INFO
crowsnest_capabilities.egg-info/SOURCES.txt
crowsnest_capabilities.egg-info/dependency_links.txt
crowsnest_capabilities.egg-info/not-zip-safe
crowsnest_capabilities.egg-info/requires.txt
crowsnest_capabilities.egg-info/top_level.txt
crowsnest_capabilities/definitions/camera.yml
crowsnest_capabilities/definitions/generic.yml
crowsnest_capabilities/definitions/sensor.yml
crowsnest_capabilities/tests/__init__.py
crowsnest_capabilities/tests/base.py
crowsnest_capabilities/tests/loader.py
crowsnest_capabilities/tests/models.py
crowsnest_capabilities/tests/structure.py