Metadata-Version: 1.1
Name: crowsnest-capabilities
Version: 0.1.1
Summary: High-level language for Crowsnest API and plugin systm
Home-page: UNKNOWN
Author: Ian A Wilson
Author-email: UNKNOWN
License: UNKNOWN
Platform: UNKNOWN
Classifier: Intended Audience :: Developers
Classifier: Intended Audience :: Information Technology
Classifier: License :: OSI Approved :: MIT License
Classifier: Programming Language :: Python
